txtpack/__init__.py
txtpack/cli.py
txtpack/content_parsing.py
txtpack/delimiter_processing.py
txtpack/file_operations.py
txtpack/main.py
txtpack/pattern_matching.py
txtpack/pipeline.py
txtpack-1.2.0.dist-info/METADATA
txtpack-1.2.0.dist-info/WHEEL
txtpack-1.2.0.dist-info/entry_points.txt
txtpack-1.2.0.dist-info/licenses/LICENSE
txtpack-1.2.0.dist-info/RECORD
