Metadata-Version: 2.4
Name: txtpack
Version: 1.2.0
Summary: Pack/unpack multiple files into a single file
License-Expression: MIT
License-File: LICENSE
Requires-Python: >=3.11
Requires-Dist: structlog>=25.4.0
Requires-Dist: typer>=0.17.4
